setup.cfg
setup.py
magistral/Message.py
magistral/__init__.py
magistral.egg-info/PKG-INFO
magistral.egg-info/SOURCES.txt
magistral.egg-info/dependency_links.txt
magistral.egg-info/requires.txt
magistral.egg-info/top_level.txt
magistral/client/Configs.py
magistral/client/IAccessControl.py
magistral/client/IHistory.py
magistral/client/IMagistral.py
magistral/client/Magistral.py
magistral/client/MagistralException.py
magistral/client/MagistralExceptionType.py
magistral/client/__init__.py
magistral/client/data/__init__.py
magistral/client/perm/PermMeta.py
magistral/client/perm/__init__.py
magistral/client/pub/Producer.py
magistral/client/pub/PubMeta.py
magistral/client/pub/__init__.py
magistral/client/sub/GroupConsumer.py
magistral/client/sub/MagistralConsumer.py
magistral/client/sub/SubMeta.py
magistral/client/sub/__init__.py
magistral/client/topics/TopicMeta.py
magistral/client/topics/__init__.py
magistral/client/util/JksHandler.py
magistral/client/util/JsonConverter.py
magistral/client/util/RestApiManager.py
magistral/client/util/__init__.py
magistral/client/util/aes.py