Metadata-Version: 1.1
Name: magistral
Version: 0.5.13
Summary: Python SDK for Magistral
Home-page: https://github.com/magistral-io/MagistralPython
Author: Magistral.IO team
Author-email: admin@magistral.io
License: UNKNOWN
Download-URL: https://github.com/magistral-io/MagistralPython/tarball/0.5.13
Keywords: magistral,sdk,messaging
Platform: UNKNOWN
